fairspace_pipeline/__init__.py
fairspace_pipeline/pipeline.py
fairspace_pipeline/api_client/__init__.py
fairspace_pipeline/api_client/fairspace_api_client.py
fairspace_pipeline/graph/__init__.py
fairspace_pipeline/graph/fairspace_graph.py
fairspace_pipeline/graph/taxonomy_graph.py
fairspace_pipeline/io_handler/__init__.py
fairspace_pipeline/io_handler/aws_s3_io_handler.py
fairspace_pipeline/io_handler/io_handler_interface.py
fairspace_pipeline/io_handler/local_io_handler.py
fairspace_pipeline-0.1.1.dist-info/LICENSE
fairspace_pipeline-0.1.1.dist-info/METADATA
fairspace_pipeline-0.1.1.dist-info/WHEEL
fairspace_pipeline-0.1.1.dist-info/top_level.txt
fairspace_pipeline-0.1.1.dist-info/RECORD
